bee_psd/__init__.py
bee_psd/_psd.py
bee_psd/builder.py
bee_psd/clause.py
bee_psd/column.py
bee_psd/criteria.py
bee_psd/db.py
bee_psd/delete.py
bee_psd/exector.py
bee_psd/insert.py
bee_psd/orm.py
bee_psd/result.py
bee_psd/select.py
bee_psd/table.py
bee_psd/update.py
bee_psd/value.py
bee_psd/abbr/__init__.py
bee_psd/abbr/abbr.py
bee_psd/connection/__init__.py
bee_psd/connection/builder.py
bee_psd/connection/connection.py
bee_psd/connection/mssql.py
bee_psd/connection/mysql.py
bee_psd/connection/sqlite.py
bee_psd/filter/__init__.py
bee_psd/provider/__init__.py
bee_psd/provider/provider.py
bee_psd/proxy/__init__.py
py_bee_psd-0.1.0.dist-info/LICENSE.rst
py_bee_psd-0.1.0.dist-info/METADATA
py_bee_psd-0.1.0.dist-info/WHEEL
py_bee_psd-0.1.0.dist-info/top_level.txt
py_bee_psd-0.1.0.dist-info/RECORD
