Metadata-Version: 2.1
Name: py-bee-psd
Version: 0.1.0
Summary: Bee is an all-in-one python framework for simplifying micro service program development.
Home-page: https://github.com/py-bee/bee-psd
Author: wenchao.hao
Author-email: awenhaowenchao@hotmail.com
License: MIT
Platform: UNKNOWN
Classifier: License :: OSI Approved :: MIT License
Classifier: Programming Language :: Python
Classifier: Programming Language :: Python :: 3
Classifier: Programming Language :: Python :: 3.6
Classifier: Programming Language :: Python :: Implementation :: CPython
Classifier: Programming Language :: Python :: Implementation :: PyPy
Requires-Python: >=3.6.0
Requires-Dist: gevent (==1.4.0)
Requires-Dist: greenlet (==1.0.0)
Requires-Dist: py-bee-config (==0.1.0)
Requires-Dist: py-bee-util (==0.1.1)
Requires-Dist: PyMySQL (==1.0.2)
Requires-Dist: PyYAML (==5.4.1)
Requires-Dist: typing-extensions (==3.7.4.3)
